django_slugger-1.1.2.dist-info/LICENSE.txt
django_slugger-1.1.2.dist-info/METADATA
django_slugger-1.1.2.dist-info/RECORD
django_slugger-1.1.2.dist-info/WHEEL
django_slugger-1.1.2.dist-info/top_level.txt
slugger/__init__.py
slugger/fields.py
