Metadata-Version: 2.1
Name: django-slugger
Version: 1.1.2
Summary: Automatic slug field for Django.
Home-page: https://gitlab.com/dspechnikov/django-slugger/
Author: Dmitry Pechnikov
Author-email: dspechnikov@gmail.com
License: MIT
Keywords: django field slug auto
Platform: UNKNOWN
Classifier: Development Status :: 5 - Production/Stable
Classifier: Environment :: Web Environment
Classifier: Framework :: Django
Classifier: Framework :: Django :: 1.11
Classifier: Framework :: Django :: 2.0
Classifier: Intended Audience :: Developers
Classifier: License :: OSI Approved :: MIT License
Classifier: Programming Language :: Python
Classifier: Programming Language :: Python :: 3
Classifier: Programming Language :: Python :: 3.6
Classifier: Programming Language :: Python :: 3.7
Requires-Dist: django
Requires-Dist: unidecode
